hanga-0.7.1.dist-info/entry_points.txt
hanga-0.7.1.dist-info/RECORD
hanga-0.7.1.dist-info/DESCRIPTION.rst
hanga-0.7.1.dist-info/top_level.txt
hanga-0.7.1.dist-info/WHEEL
hanga-0.7.1.dist-info/METADATA
hanga-0.7.1.dist-info/metadata.json
hanga/api.py
hanga/utils.py
hanga/appdirs.py
hanga/__init__.py
hanga/scripts/client.py
hanga/scripts/__init__.py
