Metadata-Version: 2.0
Name: hanga
Version: 0.7.1
Summary: Hanga client - Build automation for Python applications targeting mobile devices.
Home-page: http://hanga.io
Author: Mathieu Virbel
Author-email: mat@hanga.io
License: MIT
Keywords: build,android,buildozer,kivy
Platform: any
Classifier: Development Status :: 4 - Beta
Classifier: Intended Audience :: Developers
Classifier: Intended Audience :: End Users/Desktop
Classifier: Intended Audience :: Information Technology
Classifier: Intended Audience :: Science/Research
Classifier: Intended Audience :: System Administrators
Classifier: License :: OSI Approved :: MIT License
Classifier: Operating System :: POSIX
Classifier: Operating System :: MacOS
Classifier: Operating System :: Unix
Classifier: Programming Language :: Python
Classifier: Programming Language :: Python :: 2
Classifier: Programming Language :: Python :: 3
Classifier: Topic :: Software Development :: Libraries :: Python Modules
Classifier: Topic :: Software Development :: Build Tools
Classifier: Topic :: Internet
Classifier: Topic :: System :: Systems Administration
Classifier: Topic :: System :: Monitoring
Requires-Dist: requests (>=2.2.1)
Requires-Dist: buildozer (>=0.13)
Requires-Dist: progressbar2 (>=2.6.0)
Requires-Dist: docopt (>=0.6.1)
